odoo9_addon_contract_recurring_analytic_distribution-9.0.1.0.0-py2.7-nspkg.pth
odoo9_addon_contract_recurring_analytic_distribution-9.0.1.0.0.dist-info/DESCRIPTION.rst
odoo9_addon_contract_recurring_analytic_distribution-9.0.1.0.0.dist-info/METADATA
odoo9_addon_contract_recurring_analytic_distribution-9.0.1.0.0.dist-info/RECORD
odoo9_addon_contract_recurring_analytic_distribution-9.0.1.0.0.dist-info/WHEEL
odoo9_addon_contract_recurring_analytic_distribution-9.0.1.0.0.dist-info/metadata.json
odoo9_addon_contract_recurring_analytic_distribution-9.0.1.0.0.dist-info/namespace_packages.txt
odoo9_addon_contract_recurring_analytic_distribution-9.0.1.0.0.dist-info/top_level.txt
odoo_addons/contract_recurring_analytic_distribution/README.rst
odoo_addons/contract_recurring_analytic_distribution/__init__.py
odoo_addons/contract_recurring_analytic_distribution/__openerp__.py
odoo_addons/contract_recurring_analytic_distribution/i18n/ca.po
odoo_addons/contract_recurring_analytic_distribution/i18n/de.po
odoo_addons/contract_recurring_analytic_distribution/i18n/el_GR.po
odoo_addons/contract_recurring_analytic_distribution/i18n/es.po
odoo_addons/contract_recurring_analytic_distribution/i18n/es_MX.po
odoo_addons/contract_recurring_analytic_distribution/i18n/fi.po
odoo_addons/contract_recurring_analytic_distribution/i18n/fr.po
odoo_addons/contract_recurring_analytic_distribution/i18n/pt_BR.po
odoo_addons/contract_recurring_analytic_distribution/i18n/sk_SK.po
odoo_addons/contract_recurring_analytic_distribution/i18n/sl.po
odoo_addons/contract_recurring_analytic_distribution/models/__init__.py
odoo_addons/contract_recurring_analytic_distribution/models/account_analytic_invoice_line.py
odoo_addons/contract_recurring_analytic_distribution/static/description/icon.png
odoo_addons/contract_recurring_analytic_distribution/static/description/icon.svg
odoo_addons/contract_recurring_analytic_distribution/tests/__init__.py
odoo_addons/contract_recurring_analytic_distribution/tests/test_contract_recurring_distribution.py
odoo_addons/contract_recurring_analytic_distribution/views/account_analytic_invoice_line_view.xml
